d2b_compile.py
d2b_compile-1.1.0.dist-info/entry_points.txt
d2b_compile-1.1.0.dist-info/WHEEL
d2b_compile-1.1.0.dist-info/METADATA
d2b_compile-1.1.0.dist-info/RECORD
