Metadata-Version: 2.1
Name: d2b-compile
Version: 1.1.0
Summary: compile-dcm2bids-config plugin for the d2b package
Home-page: https://github.com/d2b-dev/d2b-compile
Keywords: neuroscience,neuroimaging,bids,plugin,d2b
Author: Alec Ross
Author-email: alexander.w.rosss@gmail.com
Requires-Python: >=3.8,<4.0
Classifier: Intended Audience :: Developers
Classifier: Intended Audience :: Healthcare Industry
Classifier: Intended Audience :: Science/Research
Classifier: Operating System :: MacOS
Classifier: Operating System :: Microsoft :: Windows
Classifier: Operating System :: Unix
Classifier: Programming Language :: Python
Classifier: Programming Language :: Python :: 3
Classifier: Programming Language :: Python :: 3.10
Classifier: Programming Language :: Python :: 3.8
Classifier: Programming Language :: Python :: 3.9
Classifier: Topic :: Scientific/Engineering
Classifier: Topic :: Scientific/Engineering :: Bio-Informatics
Classifier: Topic :: Scientific/Engineering :: Medical Science Apps.
Classifier: Topic :: Software Development :: Libraries :: Python Modules
Classifier: Topic :: Utilities
Classifier: Typing :: Typed
Requires-Dist: compile-dcm2bids-config (>=1.4.3,<2.0.0)
Requires-Dist: d2b (>=1.0.0,<2.0.0)
Project-URL: Documentation, https://github.com/d2b-dev/d2b-compile
Project-URL: Repository, https://github.com/d2b-dev/d2b-compile
